MCServerLib/Server.py
MCServerLib/__init__.py
MCServerLib-0.2.5.dist-info/LICENSE
MCServerLib-0.2.5.dist-info/METADATA
MCServerLib-0.2.5.dist-info/WHEEL
MCServerLib-0.2.5.dist-info/top_level.txt
MCServerLib-0.2.5.dist-info/RECORD
