Metadata-Version: 2.1
Name: MCServerLib
Version: 0.2.5
Summary: Minecraft Server Setup Library
Home-page: https://github.com/myoung2namur/MCServerLib
Author: 명이
Author-email: aiden080605@gmail.com
License: UNKNOWN
Platform: UNKNOWN
Classifier: Programming Language :: Python :: 3
Classifier: License :: OSI Approved :: MIT License
Classifier: Operating System :: OS Independent
Requires-Python: >=3.6
Requires-Dist: cpython
